py_dem_bones/__init__.py
py_dem_bones/__init__.pyi
py_dem_bones/__version__.py
py_dem_bones/_py_dem_bones.cp310-win_amd64.pyd
py_dem_bones/_py_dem_bones.pyi
py_dem_bones/base.py
py_dem_bones/base.pyi
py_dem_bones/exceptions.py
py_dem_bones/exceptions.pyi
py_dem_bones/interfaces/__init__.py
py_dem_bones/interfaces/__init__.pyi
py_dem_bones/interfaces/dcc.py
py_dem_bones/interfaces/dcc.pyi
py_dem_bones/utils.py
py_dem_bones/utils.pyi
py_dem_bones-0.12.4.dist-info/METADATA
py_dem_bones-0.12.4.dist-info/WHEEL
py_dem_bones-0.12.4.dist-info/licenses/LICENSE.md
py_dem_bones-0.12.4.dist-info/RECORD
